{
  "utilisateurs": [
    {
      "username": "programmer",
      "password": "programmer1234",
      "email": "programmer@gmail.com"
    }
  ],
  "seances": [
    {
      "idSeance": "test",
      "professeur": "asdf",
      "matiere": "good",
      "salle": "salleM",
      "dateSeance": "02/21/2024"
    },
    {
      "idSeance": "seancePrograming",
      "professeur": "adam04",
      "matiere": "newId",
      "salle": "salleM",
      "dateSeance": "02/22/2024"
    },
    {
      "idSeance": "45",
      "professeur": "asdf",
      "matiere": "newId",
      "salle": "salleM",
      "dateSeance": "05/20/2024"
    }
  ],
  "professeurs": [
    {
      "nom": "ans",
      "prenom": "ans",
      "cin": "kl1414",
      "filiere": "khiyata",
      "matricule": "khiyata400"
    },
    {
      "nom": "Adam",
      "prenom": "Jeniah",
      "cin": "kb5500",
      "filiere": "programing",
      "matricule": "prog123"
    },
    {
      "nom": "adam",
      "prenom": "jeniah",
      "cin": "programing",
      "filiere": "kb243538",
      "matricule": "adam04"
    },
    {
      "nom": "test",
      "prenom": "sd",
      "cin": "asdfa",
      "filiere": "asdfasd",
      "matricule": "asdf"
    }
  ],
  "matieres": [
    {
      "idMatiere": "good",
      "libelle": "good",
      "langue": "english"
    },
    {
      "idMatiere": "newId",
      "libelle": "libelle",
      "langue": "math"
    }
  ],
  "salles": [
    {
      "idSalle": "newSalle",
      "libelle": "math",
      "numero": 7000
    }
  ],
  "apprenants": [
    {
      "nom": "jeniah",
      "prenom": "adam",
      "cin": "kb243538",
      "niveau": "2anne",
      "age": 19
    },
    {
      "nom": "jeniah",
      "prenom": "prenom",
      "cin": "kb248",
      "niveau": "2anne",
      "age": 19
    }
  ],
  "responsables": [
    {
      "nom": "mohamed",
      "prenom": "jeniah",
      "cin": "kb234",
      "responsabilite": "etudiant",
      "matricule": "1234"
    }
  ]
}